Workbook

Sheet Sheet1
A1: Country | B1: Subnational region | C1: Malaria Incidence | D1: IVM Target Population | E1: IVM Coverage | F1: ALBIVM Target Population | G1: ALBIVM Coverage | H1: Total population | I1: Prevalence of Loa Loa | J1: Uncomplicated malaria cases (per 100 000) | K1: Severe Malaria Cases (per 100000) | L1: Estimated Uncomplicated Cases | M1: Estimated Severe Cases | N1: Cost inpatient bed day at Secondary level (US$ 2024) | O1: Cost per outpatient in health center (US$ 2024) | P1: Unit cost Uncomplicated | Q1: Unit Cost Severe | R1: DALYS malaria | S1: Programme Cost | T1: Incidence Rate (cases per thousand) | U1: Total Malaria Cases (Estimated)
A2: Angola | B2: Bengo | C2: 166425.88 | F2: 0 | G2: 235300 | H2: 537916 | I2: 30.465833 | J2: 689.7 | K2: 296.1 | L2: =IFERROR($H2*J2/100000,"") -> 3710.0067 | M2: =IFERROR($H2*K2/100000,"") -> 1592.7693 | N2: 49.2528 | O2: 6.5516 | P2: 9.79 | Q2: 69.055 | R2: 0.198 | S2: 56732.311 | T2: 200.77 | U2: =IFERROR($T2*$H2/1000,"") -> 107997.4
A3: Angola | B3: Bie | C3: 346453.99 | D3: 1442146 | E3: 1026886 | F3: 62229 | G3: 27610 | H3: 2043741 | I3: 22.409444 | J3: 689.7 | K3: 296.1 | L3: =IFERROR($H3*J3/100000,"") -> 14095.682 | M3: =IFERROR($H3*K3/100000,"") -> 6051.5171 | N3: 49.2528 | O3: 6.5516 | P3: 9.79 | Q3: 69.055 | R3: 0.198 | S3: 56732.311 | T3: 309.893 | U3: =IFERROR($T3*$H3/1000,"") -> 633341.03
A4: Angola | B4: Cuando Cubango | C4: 117611.63 | D4: 468242 | E4: 275097 | H4: 737307 | I4: 24.222778 | J4: 689.7 | K4: 296.1 | L4: =IFERROR($H4*J4/100000,"") -> 5085.2064 | M4: =IFERROR($H4*K4/100000,"") -> 2183.166 | N4: 49.2528 | O4: 6.5516 | P4: 9.79 | Q4: 69.055 | R4: 0.198 | S4: 56732.311 | T4: 253.497 | U4: =IFERROR($T4*$H4/1000,"") -> 186905.11
A5: Angola | B5: Cuanza Norte | C5: 110068.67 | F5: 134245 | G5: 197536 | H5: 604659 | I5: 11.254 | J5: 689.7 | K5: 296.1 | L5: =IFERROR($H5*J5/100000,"") -> 4170.3331 | M5: =IFERROR($H5*K5/100000,"") -> 1790.3953 | N5: 49.2528 | O5: 6.5516 | P5: 9.79 | Q5: 69.055 | R5: 0.198 | S5: 56732.311 | T5: 341.788 | U5: =IFERROR($T5*$H5/1000,"") -> 206665.19
A6: Angola | B6: Cuanza Sul | C6: 694473.42 | D6: 88063 | E6: 43292 | F6: 134388 | G6: 65863 | H6: 2580986 | I6: 9.74375 | J6: 689.7 | K6: 296.1 | L6: =IFERROR($H6*J6/100000,"") -> 17801.06 | M6: =IFERROR($H6*K6/100000,"") -> 7642.2995 | N6: 49.2528 | O6: 6.5516 | P6: 9.79 | Q6: 69.055 | R6: 0.198 | S6: 56732.311 | T6: 354.065 | U6: =IFERROR($T6*$H6/1000,"") -> 913836.81
A7: Angola | B7: Huambo | C7: 616511.62 | D7: 125195 | E7: 89663 | H7: 2865919 | I7: 6.355 | J7: 689.7 | K7: 296.1 | L7: =IFERROR($H7*J7/100000,"") -> 19766.243 | M7: =IFERROR($H7*K7/100000,"") -> 8485.9862 | N7: 49.2528 | O7: 6.5516 | P7: 9.79 | Q7: 69.055 | R7: 0.198 | S7: 56732.311 | T7: 353.293 | U7: =IFERROR($T7*$H7/1000,"") -> 1012509.1
A8: Angola | B8: Huila | C8: 961330.34 | D8: 872419 | E8: 538474 | F8: 69808 | G8: 161848 | H8: 3463351 | I8: 2.0621429 | J8: 689.7 | K8: 296.1 | L8: =IFERROR($H8*J8/100000,"") -> 23886.732 | M8: =IFERROR($H8*K8/100000,"") -> 10254.982 | N8: 49.2528 | O8: 6.5516 | P8: 9.79 | Q8: 69.055 | R8: 0.198 | S8: 56732.311 | T8: 289.84 | U8: =IFERROR($T8*$H8/1000,"") -> 1003817.7
A9: Angola | B9: Lunda Sul | C9: 139008.24 | D9: 68671 | E9: 44752 | F9: 514948 | G9: 195824 | H9: 750284 | I9: 1.33375 | J9: 689.7 | K9: 296.1 | L9: =IFERROR($H9*J9/100000,"") -> 5174.7087 | M9: =IFERROR($H9*K9/100000,"") -> 2221.5909 | N9: 49.2528 | O9: 6.5516 | P9: 9.79 | Q9: 69.055 | R9: 0.198 | S9: 56732.311 | T9: 256.389 | U9: =IFERROR($T9*$H9/1000,"") -> 192364.56
A10: Angola | B10: Uige | C10: 354487.75 | D10: 186245 | E10: 146735 | F10: 142728 | G10: 125010 | H10: 2032514 | I10: 7.685 | J10: 689.7 | K10: 296.1 | L10: =IFERROR($H10*J10/100000,"") -> 14018.249 | M10: =IFERROR($H10*K10/100000,"") -> 6018.274 | N10: 49.2528 | O10: 6.5516 | P10: 9.79 | Q10: 69.055 | R10: 0.198 | S10: 56732.311 | T10: 375.283 | U10: =IFERROR($T10*$H10/1000,"") -> 762767.95
A11: Benin | B11: Alibori | C11: 523611.09 | D11: 899911 | E11: 761218 | H11: 1092654 | I11: 0 | J11: 628.9 | K11: 225.4 | L11: =IFERROR($H11*J11/100000,"") -> 6871.701 | M11: =IFERROR($H11*K11/100000,"") -> 2462.8421 | N11: 8.0538 | O11: 1.65 | P11: 4.1 | Q11: 102.025 | R11: 0.197 | S11: 182830.4 | T11: 377.763 | U11: =IFERROR($T11*$H11/1000,"") -> 412764.25
A12: Benin | B12: Atakora | C12: 459453.55 | D12: 720007 | E12: 673607 | H12: 972740 | I12: 0 | J12: 628.9 | K12: 225.4 | L12: =IFERROR($H12*J12/100000,"") -> 6117.5619 | M12: =IFERROR($H12*K12/100000,"") -> 2192.556 | N12: 8.0538 | O12: 1.65 | P12: 4.1 | Q12: 102.025 | R12: 0.197 | S12: 182830.4 | T12: 388.753 | U12: =IFERROR($T12*$H12/1000,"") -> 378155.59
A13: Benin | B13: Atlantique | C13: 805362.62 | D13: 32367 | E13: 28345 | H13: 1761206 | I13: 0 | J13: 628.9 | K13: 225.4 | L13: =IFERROR($H13*J13/100000,"") -> 11076.225 | M13: =IFERROR($H13*K13/100000,"") -> 3969.7583 | N13: 8.0538 | O13: 1.65 | P13: 4.1 | Q13: 102.025 | R13: 0.197 | S13: 182830.4 | T13: 353.688 | U13: =IFERROR($T13*$H13/1000,"") -> 622917.43
A14: Benin | B14: Borgou | C14: 711488.7 | D14: 1259669 | E14: 1042667 | H14: 1529465 | I14: 0 | J14: 628.9 | K14: 225.4 | L14: =IFERROR($H14*J14/100000,"") -> 9618.8054 | M14: =IFERROR($H14*K14/100000,"") -> 3447.4141 | N14: 8.0538 | O14: 1.65 | P14: 4.1 | Q14: 102.025 | R14: 0.197 | S14: 182830.4 | T14: 372.001 | U14: =IFERROR($T14*$H14/1000,"") -> 568962.51
A15: Benin | B15: Collines | C15: 380559.94 | D15: 744315 | E15: 614893 | H15: 903733 | I15: 0 | J15: 628.9 | K15: 225.4 | L15: =IFERROR($H15*J15/100000,"") -> 5683.5768 | M15: =IFERROR($H15*K15/100000,"") -> 2037.0142 | N15: 8.0538 | O15: 1.65 | P15: 4.1 | Q15: 102.025 | R15: 0.197 | S15: 182830.4 | T15: 386.839 | U15: =IFERROR($T15*$H15/1000,"") -> 349599.17
A16: Benin | B16: Couffo | C16: 403346.33 | D16: 587470 | E16: 434102 | H16: 938813 | I16: 0 | J16: 628.9 | K16: 225.4 | L16: =IFERROR($H16*J16/100000,"") -> 5904.195 | M16: =IFERROR($H16*K16/100000,"") -> 2116.0845 | N16: 8.0538 | O16: 1.65 | P16: 4.1 | Q16: 102.025 | R16: 0.197 | S16: 182830.4 | T16: 380.465 | U16: =IFERROR($T16*$H16/1000,"") -> 357185.49
A17: Benin | B17: Donga | C17: 317117.3 | D17: 563444 | E17: 484339 | H17: 684124 | I17: 0 | J17: 628.9 | K17: 225.4 | L17: =IFERROR($H17*J17/100000,"") -> 4302.4558 | M17: =IFERROR($H17*K17/100000,"") -> 1542.0155 | N17: 8.0538 | O17: 1.65 | P17: 4.1 | Q17: 102.025 | R17: 0.197 | S17: 182830.4 | T17: 393.829 | U17: =IFERROR($T17*$H17/1000,"") -> 269427.87
A18: Benin | B18: Mono | C18: 262885.26 | D18: 74233 | E18: 58443 | H18: 626326 | I18: 0 | J18: 628.9 | K18: 225.4 | L18: =IFERROR($H18*J18/100000,"") -> 3938.9642 | M18: =IFERROR($H18*K18/100000,"") -> 1411.7388 | N18: 8.0538 | O18: 1.65 | P18: 4.1 | Q18: 102.025 | R18: 0.197 | S18: 182830.4 | T18: 379.063 | U18: =IFERROR($T18*$H18/1000,"") -> 237417.01
A19: Benin | B19: Oueme | C19: 525653.77 | D19: 46008 | E19: 36464 | H19: 1438490 | I19: 0 | J19: 628.9 | K19: 225.4 | L19: =IFERROR($H19*J19/100000,"") -> 9046.6636 | M19: =IFERROR($H19*K19/100000,"") -> 3242.3565 | N19: 8.0538 | O19: 1.65 | P19: 4.1 | Q19: 102.025 | R19: 0.197 | S19: 182830.4 | T19: 322.992 | U19: =IFERROR($T19*$H19/1000,"") -> 464620.76
A20: Benin | B20: Plateau | C20: 365150.01 | D20: 283869 | E20: 224604 | H20: 783938 | I20: 0 | J20: 628.9 | K20: 225.4 | L20: =IFERROR($H20*J20/100000,"") -> 4930.1861 | M20: =IFERROR($H20*K20/100000,"") -> 1766.9963 | N20: 8.0538 | O20: 1.65 | P20: 4.1 | Q20: 102.025 | R20: 0.197 | S20: 182830.4 | T20: 396.753 | U20: =IFERROR($T20*$H20/1000,"") -> 311029.75
A21: Benin | B21: Zou | C21: 448421.72 | D21: 562159 | E21: 481134 | H21: 1072649 | I21: 0 | J21: 628.9 | K21: 225.4 | L21: =IFERROR($H21*J21/100000,"") -> 6745.8896 | M21: =IFERROR($H21*K21/100000,"") -> 2417.7508 | N21: 8.0538 | O21: 1.65 | P21: 4.1 | Q21: 102.025 | R21: 0.197 | S21: 182830.4 | T21: 363.117 | U21: =IFERROR($T21*$H21/1000,"") -> 389497.09
A22: Burkina Faso | B22: Cascades | C22: 310345.08 | D22: 62326 | E22: 62322 | H22: 940692 | I22: 0 | J22: 2209.5 | K22: 427.2 | L22: =IFERROR($H22*J22/100000,"") -> 20784.59 | M22: =IFERROR($H22*K22/100000,"") -> 4018.6362 | N22: 6.5466 | O22: 1.4119 | P22: 4.1 | Q22: 102.025 | R22: 0.221 | S22: 1178887 | T22: 249.441 | U22: =IFERROR($T22*$H22/1000,"") -> 234647.15
A23: Burkina Faso | B23: Sud-Ouest | C23: 283876.61 | D23: 165625 | E23: 164321 | F23: =SUM(55716+101548) -> 157264 | G23: =SUM(55716+100862) -> 156578 | H23: 1013635 | I23: 0 | J23: 2209.5 | K23: 427.2 | L23: =IFERROR($H23*J23/100000,"") -> 22396.265 | M23: =IFERROR($H23*K23/100000,"") -> 4330.2487 | N23: 6.5466 | O23: 1.4119 | P23: 4.1 | Q23: 102.025 | R23: 0.221 | S23: 1178887 | T23: 279.393 | U23: =IFERROR($T23*$H23/1000,"") -> 283202.52
A24: Burundi | B24: Bubanza | C24: 124263.97 | D24: 568093 | E24: 464384 | H24: 560452 | I24: 0 | J24: 1081.3 | K24: 337.5 | L24: =IFERROR($H24*J24/100000,"") -> 6060.1675 | M24: =IFERROR($H24*K24/100000,"") -> 1891.5255 | N24: 1.8829 | O24: 0.5436 | P24: 3.18 | Q24: 36.035 | R24: 0.164 | S24: 349502.26 | T24: 236.61 | U24: =IFERROR($T24*$H24/1000,"") -> 132608.55
A25: Burundi | B25: Bujumbura (Mairie) | C25: 209761.07 | D25: 89366 | E25: 73166 | H25: 824315 | I25: 0 | J25: 1081.3 | K25: 337.5 | L25: =IFERROR($H25*J25/100000,"") -> 8913.3181 | M25: =IFERROR($H25*K25/100000,"") -> 2782.0631 | N25: 1.8829 | O25: 0.5436 | P25: 3.18 | Q25: 36.035 | R25: 0.164 | S25: 349502.26 | T25: 202.345 | U25: =IFERROR($T25*$H25/1000,"") -> 166796.02
A26: Burundi | B26: Bururi | C26: 33985.557 | D26: 458839 | E26: 373471 | H26: 856945 | I26: 0 | J26: 1081.3 | K26: 337.5 | L26: =IFERROR($H26*J26/100000,"") -> 9266.1463 | M26: =IFERROR($H26*K26/100000,"") -> 2892.1894 | N26: 1.8829 | O26: 0.5436 | P26: 3.18 | Q26: 36.035 | R26: 0.164 | S26: 349502.26 | T26: 58.528 | U26: =IFERROR($T26*$H26/1000,"") -> 50155.277
A27: Burundi | B27: Cibitoke | C27: 183081.6 | D27: 814665 | E27: 666112 | H27: 763414 | I27: 0 | J27: 1081.3 | K27: 337.5 | L27: =IFERROR($H27*J27/100000,"") -> 8254.7956 | M27: =IFERROR($H27*K27/100000,"") -> 2576.5222 | N27: 1.8829 | O27: 0.5436 | P27: 3.18 | Q27: 36.035 | R27: 0.164 | S27: 349502.26 | T27: 228.415 | U27: =IFERROR($T27*$H27/1000,"") -> 174375.21
A28: Burundi | B28: Makamba | C28: 165715.69 | D28: 80692 | E28: 67208 | H28: 714443 | I28: 0 | J28: 1081.3 | K28: 337.5 | L28: =IFERROR($H28*J28/100000,"") -> 7725.2722 | M28: =IFERROR($H28*K28/100000,"") -> 2411.2451 | N28: 1.8829 | O28: 0.5436 | P28: 3.18 | Q28: 36.035 | R28: 0.164 | S28: 349502.26 | T28: 231.173 | U28: =IFERROR($T28*$H28/1000,"") -> 165159.93
A29: Burundi | B29: Rutana | C29: 171153.98 | D29: 361670 | E29: 292886 | H29: 552970 | I29: 0 | J29: 1081.3 | K29: 337.5 | L29: =IFERROR($H29*J29/100000,"") -> 5979.2646 | M29: =IFERROR($H29*K29/100000,"") -> 1866.2738 | N29: 1.8829 | O29: 0.5436 | P29: 3.18 | Q29: 36.035 | R29: 0.164 | S29: 349502.26 | T29: 247.812 | U29: =IFERROR($T29*$H29/1000,"") -> 137032.6
A30: Cameroon | B30: Est | C30: 450062.58 | D30: 291555 | E30: 144005 | H30: 1469352 | I30: 56.433667 | J30: 1829 | K30: 240.1 | L30: =IFERROR($H30*J30/100000,"") -> 26874.448 | M30: =IFERROR($H30*K30/100000,"") -> 3527.9142 | N30: 13.7352 | O30: 2.4918 | P30: 9.79 | Q30: 69.05 | R30: 0.128 | S30: 291013.33 | T30: 338.012 | U30: =IFERROR($T30*$H30/1000,"") -> 496658.61
A31: Cameroon | B31: Extreme Nord | C31: 1421022.8 | D31: 601341 | E31: 378419 | H31: 5358825 | I31: 0.001515152 | J31: 1829 | K31: 240.1 | L31: =IFERROR($H31*J31/100000,"") -> 98012.909 | M31: =IFERROR($H31*K31/100000,"") -> 12866.539 | N31: 13.7352 | O31: 2.4918 | P31: 9.79 | Q31: 69.05 | R31: 0.128 | S31: 291013.33 | T31: 239.306 | U31: =IFERROR($T31*$H31/1000,"") -> 1282399
A32: Cameroon | B32: Littoral | C32: 1429297.5 | D32: 684587 | E32: 396616 | H32: 4487972 | I32: 31.910833 | J32: 1829 | K32: 240.1 | L32: =IFERROR($H32*J32/100000,"") -> 82085.008 | M32: =IFERROR($H32*K32/100000,"") -> 10775.621 | N32: 13.7352 | O32: 2.4918 | P32: 9.79 | Q32: 69.05 | R32: 0.128 | S32: 291013.33 | T32: 259.309 | U32: =IFERROR($T32*$H32/1000,"") -> 1163771.5
A33: Cameroon | B33: Nord | C33: 1029496.4 | D33: 1271317 | E33: 946109 | H33: 3242725 | I33: 0.80166667 | J33: 1829 | K33: 240.1 | L33: =IFERROR($H33*J33/100000,"") -> 59309.44 | M33: =IFERROR($H33*K33/100000,"") -> 7785.7827 | N33: 13.7352 | O33: 2.4918 | P33: 9.79 | Q33: 69.05 | R33: 0.128 | S33: 291013.33 | T33: 262.454 | U33: =IFERROR($T33*$H33/1000,"") -> 851066.15
A34: Cameroon | B34: Nord Ouest | C34: 600703.3 | D34: 1692293 | E34: 1171244 | H34: 2048193 | I34: 21.452857 | J34: 1829 | K34: 240.1 | L34: =IFERROR($H34*J34/100000,"") -> 37461.45 | M34: =IFERROR($H34*K34/100000,"") -> 4917.7114 | N34: 13.7352 | O34: 2.4918 | P34: 9.79 | Q34: 69.05 | R34: 0.128 | S34: 291013.33 | T34: 210.509 | U34: =IFERROR($T34*$H34/1000,"") -> 431163.06
A35: Cameroon | B35: Ouest | C35: 550840.05 | D35: 2067374 | E35: 2127572 | H35: 2514133 | I35: 20.62825 | J35: 1829 | K35: 240.1 | L35: =IFERROR($H35*J35/100000,"") -> 45983.493 | M35: =IFERROR($H35*K35/100000,"") -> 6036.4333 | N35: 13.7352 | O35: 2.4918 | P35: 9.79 | Q35: 69.05 | R35: 0.128 | S35: 291013.33 | T35: 206.936 | U35: =IFERROR($T35*$H35/1000,"") -> 520264.63
... A37: Cameroon | B37: Sud Ouest | C37: 646521.33 | D37: 1751337 | E37: 1150588 | H37: 2090068 | I37: 18.131429 | J37: 1829 | K37: 240.1 | L37: =IFERROR($H37*J37/100000,"") -> 38227.344 | M37: =IFERROR($H37*K37/100000,"") -> 5018.2533 | N37: 13.7352 | O37: 2.4918 | P37: 9.79 | Q37: 69.05 | R37: 0.128 | S37: 291013.33 | T37: 262.376 | U37: =IFERROR($T37*$H37/1000,"") -> 548383.68
A38: Chad | B38: Logone Occidental | C38: 167184.76 | F38: 465057 | G38: 427353 | H38: 1121837 | I38: 38.100625 | J38: 204.9 | K38: 146.2 | L38: =IFERROR($H38*J38/100000,"") -> 2298.644 | M38: =IFERROR($H38*K38/100000,"") -> 1640.1257 | N38: 8.5411 | O38: 1.7771 | P38: 9.75 | Q38: 36.035 | R38: 0.36 | S38: 188934.21 | T38: 164.084 | U38: =IFERROR($T38*$H38/1000,"") -> 184075.5
A39: Chad | B39: Logone Oriental | C39: 290005.93 | F39: 1191962 | G39: 978347 | H39: 1290288 | I39: 19.405455 | J39: 204.9 | K39: 146.2 | L39: =IFERROR($H39*J39/100000,"") -> 2643.8001 | M39: =IFERROR($H39*K39/100000,"") -> 1886.4011 | N39: 8.5411 | O39: 1.7771 | P39: 9.75 | Q39: 36.035 | R39: 0.36 | S39: 188934.21 | T39: 191.04 | U39: =IFERROR($T39*$H39/1000,"") -> 246496.62
A40: Chad | B40: Mandoul | C40: 236891.88 | D40: 672758 | E40: 574123 | F40: 270934 | G40: 216104 | H40: 1290288 | I40: 15.008333 | J40: 204.9 | K40: 146.2 | L40: =IFERROR($H40*J40/100000,"") -> 2643.8001 | M40: =IFERROR($H40*K40/100000,"") -> 1886.4011 | N40: 8.5411 | O40: 1.7771 | P40: 9.75 | Q40: 36.035 | R40: 0.36 | S40: 188934.21 | T40: 224.538 | U40: =IFERROR($T40*$H40/1000,"") -> 289718.69
A41: Chad | B41: Mayo Kebbi Est | C41: 338079.06 | D41: 550254 | E41: 455803 | F41: 53767 | G41: 43772 | H41: 1245894 | I41: 0.13884615 | J41: 204.9 | K41: 146.2 | L41: =IFERROR($H41*J41/100000,"") -> 2552.8368 | M41: =IFERROR($H41*K41/100000,"") -> 1821.497 | N41: 8.5411 | O41: 1.7771 | P41: 9.75 | Q41: 36.035 | R41: 0.36 | S41: 188934.21 | T41: 262.286 | U41: =IFERROR($T41*$H41/1000,"") -> 326780.55
A42: Chad | B42: Mayo Kebbi Ouest | C42: 271402.84 | D42: 961050 | E42: 796235 | H42: 917047 | I42: 5.4477778 | J42: 204.9 | K42: 146.2 | L42: =IFERROR($H42*J42/100000,"") -> 1879.0293 | M42: =IFERROR($H42*K42/100000,"") -> 1340.7227 | N42: 8.5411 | O42: 1.7771 | P42: 9.75 | Q42: 36.035 | R42: 0.36 | S42: 188934.21 | T42: 294.345 | U42: =IFERROR($T42*$H42/1000,"") -> 269928.2
A43: Chad | B43: Moyen Chari | C43: 270309.84 | F43: 999423 | G43: 832463 | H43: 961556 | I43: 6.295625 | J43: 204.9 | K43: 146.2 | L43: =IFERROR($H43*J43/100000,"") -> 1970.2282 | M43: =IFERROR($H43*K43/100000,"") -> 1405.7949 | N43: 8.5411 | O43: 1.7771 | P43: 9.75 | Q43: 36.035 | R43: 0.36 | S43: 188934.21 | T43: 270.662 | U43: =IFERROR($T43*$H43/1000,"") -> 260256.67
A44: Chad | B44: Tandjile | C44: 175208.68 | D44: 316256 | E44: 257862 | F44: 393110 | G44: 324151 | H44: 1082432 | I44: 14.6895 | J44: 204.9 | K44: 146.2 | L44: =IFERROR($H44*J44/100000,"") -> 2217.9032 | M44: =IFERROR($H44*K44/100000,"") -> 1582.5156 | N44: 8.5411 | O44: 1.7771 | P44: 9.75 | Q44: 36.035 | R44: 0.36 | S44: 188934.21 | T44: 169.09 | U44: =IFERROR($T44*$H44/1000,"") -> 183028.43
A45: Congo | B45: Bouenza | C45: 72396.82 | D45: 170169 | E45: 119302 | F45: 237385 | G45: 112563 | H45: 477903 | I45: 43.324 | J45: 490.1 | K45: 74.9 | L45: =IFERROR($H45*J45/100000,"") -> 2342.2026 | M45: =IFERROR($H45*K45/100000,"") -> 357.94935 | N45: 35.8824 | O45: 5.2617 | P45: 9.79 | Q45: 69.06 | R45: 0.12 | S45: 252432.76 | T45: 180.728 | U45: =IFERROR($T45*$H45/1000,"") -> 86370.453
A46: Congo | B46: Brazzaville | C46: 300088.18 | D46: 762424 | E46: 668334 | H46: 2113648 | I46: 45.62 | J46: 490.1 | K46: 74.9 | L46: =IFERROR($H46*J46/100000,"") -> 10358.989 | M46: =IFERROR($H46*K46/100000,"") -> 1583.1224 | N46: 35.8824 | O46: 5.2617 | P46: 9.79 | Q46: 69.06 | R46: 0.12 | S46: 252432.76 | T46: 249.079 | U46: =IFERROR($T46*$H46/1000,"") -> 526465.33
A47: Congo | B47: Kouilou | C47: 53965.32 | D47: 35789 | E47: 867 | H47: 151848 | I47: 32.55375 | J47: 490.1 | K47: 74.9 | L47: =IFERROR($H47*J47/100000,"") -> 744.20705 | M47: =IFERROR($H47*K47/100000,"") -> 113.73415 | N47: 35.8824 | O47: 5.2617 | P47: 9.79 | Q47: 69.06 | R47: 0.12 | S47: 252432.76 | T47: 168.012 | U47: =IFERROR($T47*$H47/1000,"") -> 25512.286
A48: Congo | B48: Lekoumou | C48: 45322.524 | D48: 85890 | E48: 696 | H48: 137286 | I48: 32.7275 | J48: 490.1 | K48: 74.9 | L48: =IFERROR($H48*J48/100000,"") -> 672.83869 | M48: =IFERROR($H48*K48/100000,"") -> 102.82721 | N48: 35.8824 | O48: 5.2617 | P48: 9.79 | Q48: 69.06 | R48: 0.12 | S48: 252432.76 | T48: 181.754 | U48: =IFERROR($T48*$H48/1000,"") -> 24952.28
A49: Congo | B49: Niari | C49: 44244.694 | F49: 166492 | G49: 22870 | H49: 370199 | I49: 35.934 | J49: 490.1 | K49: 74.9 | L49: =IFERROR($H49*J49/100000,"") -> 1814.3453 | M49: =IFERROR($H49*K49/100000,"") -> 277.27905 | N49: 35.8824 | O49: 5.2617 | P49: 9.79 | Q49: 69.06 | R49: 0.12 | S49: 252432.76 | T49: 176.985 | U49: =IFERROR($T49*$H49/1000,"") -> 65519.67
A50: Congo | B50: Pool | C50: 175826.77 | D50: 181900 | E50: 155223 | F50: 74935 | G50: 2916 | H50: 348599 | I50: 49.39062 | J50: 490.1 | K50: 74.9 | L50: =IFERROR($H50*J50/100000,"") -> 1708.4837 | M50: =IFERROR($H50*K50/100000,"") -> 261.10065 | N50: 35.8824 | O50: 5.2617 | P50: 9.79 | Q50: 69.06 | R50: 0.12 | S50: 252432.76 | T50: 306.018 | U50: =IFERROR($T50*$H50/1000,"") -> 106677.57
A51: Cote d'Ivoire | B51: Bas-Sassandra | C51: 992151.71 | D51: =SUM(425621+1076302+249280) -> 1751203 | E51: =SUM(375986+1021564+226311) -> 1623861 | H51: 2840487 | I51: 0 | J51: 184 | K51: 124.1 | L51: =IFERROR($H51*J51/100000,"") -> 5226.4961 | M51: =IFERROR($H51*K51/100000,"") -> 3525.0444 | N51: 11.7286 | O51: 2.1995 | P51: 9.79 | Q51: 97.875 | R51: 0.125 | S51: 186652.11 | T51: 275.805 | U51: =IFERROR($T51*$H51/1000,"") -> 783420.52
A52: Cote d'Ivoire | B52: Comoé | C52: 365605.29 | D52: =SUM(662947+733370) -> 1396317 | E52: =SUM(622681+643675) -> 1266356 | H52: 1587001 | I52: 0 | J52: 184 | K52: 124.1 | L52: =IFERROR($H52*J52/100000,"") -> 2920.0818 | M52: =IFERROR($H52*K52/100000,"") -> 1969.4682 | N52: 11.7286 | O52: 2.1995 | P52: 9.79 | Q52: 97.875 | R52: 0.125 | S52: 186652.11 | T52: 204.949 | U52: =IFERROR($T52*$H52/1000,"") -> 325254.27
A53: Cote d'Ivoire | B53: Denguélé | C53: 134361.03 | D53: =SUM(135797+271429) -> 407226 | E53: =+SUM(116879+251778) -> 368657 | H53: 1587001 | I53: 0 | J53: 184 | K53: 124.1 | L53: =IFERROR($H53*J53/100000,"") -> 2920.0818 | M53: =IFERROR($H53*K53/100000,"") -> 1969.4682 | N53: 11.7286 | O53: 2.1995 | P53: 9.79 | Q53: 97.875 | R53: 0.125 | S53: 186652.11 | T53: 291.463 | U53: =IFERROR($T53*$H53/1000,"") -> 462552.07
A54: Cote d'Ivoire | B54: Gôh-Djiboua | C54: 580880.57 | D54: 1027671 | E54: 944168 | H54: 2207607 | I54: 0 | J54: 184 | K54: 124.1 | L54: =IFERROR($H54*J54/100000,"") -> 4061.9969 | M54: =IFERROR($H54*K54/100000,"") -> 2739.6403 | N54: 11.7286 | O54: 2.1995 | P54: 9.79 | Q54: 97.875 | R54: 0.125 | S54: 186652.11 | T54: 228.842 | U54: =IFERROR($T54*$H54/1000,"") -> 505193.2
A55: Cote d'Ivoire | B55: Lacs | C55: 512561.8 | D55: =SUM(399787+1022127) -> 1421914 | E55: =SUM(353912+308900+376119+220170) -> 1259101 | H55: 1573468 | I55: 0 | J55: 184 | K55: 124.1 | L55: =IFERROR($H55*J55/100000,"") -> 2895.1811 | M55: =IFERROR($H55*K55/100000,"") -> 1952.6738 | N55: 11.7286 | O55: 2.1995 | P55: 9.79 | Q55: 97.875 | R55: 0.125 | S55: 186652.11 | T55: 261.076 | U55: =IFERROR($T55*$H55/1000,"") -> 410794.73
A56: Cote d'Ivoire | B56: Lagunes | C56: 468596.48 | D56: =SUM(814490+681108+203160) -> 1698758 | E56: =SUM(729705+171697+595655) -> 1497057 | H56: 8840921 | I56: 0 | J56: 184 | K56: 124.1 | L56: =IFERROR($H56*J56/100000,"") -> 16267.295 | M56: =IFERROR($H56*K56/100000,"") -> 10971.583 | N56: 11.7286 | O56: 2.1995 | P56: 9.79 | Q56: 97.875 | R56: 0.125 | S56: 186652.11 | T56: 214.01 | U56: =IFERROR($T56*$H56/1000,"") -> 1892045.5
A57: Cote d'Ivoire | B57: Montagnes | C57: 988279.89 | D57: =SUM(651748+862483+1292485) -> 2806716 | E57: =SUM(602300+816378+1137623) -> 2556301 | H57: 3199714 | I57: 0 | J57: 184 | K57: 124.1 | L57: =IFERROR($H57*J57/100000,"") -> 5887.4738 | M57: =IFERROR($H57*K57/100000,"") -> 3970.8451 | N57: 11.7286 | O57: 2.1995 | P57: 9.79 | Q57: 97.875 | R57: 0.125 | S57: 186652.11 | T57: 258.833 | U57: =IFERROR($T57*$H57/1000,"") -> 828191.57
A58: Cote d'Ivoire | B58: Sassandra-Marahoué | C58: 1059649.6 | D58: =SUM(922726+1606702+683708) -> 3213136 | E58: =SUM(849526+1448924+620984) -> 2919434 | H58: 2876120 | I58: 0 | J58: 184 | K58: 124.1 | L58: =IFERROR($H58*J58/100000,"") -> 5292.0608 | M58: =IFERROR($H58*K58/100000,"") -> 3569.2649 | N58: 11.7286 | O58: 2.1995 | P58: 9.79 | Q58: 97.875 | R58: 0.125 | S58: 186652.11 | T58: 291.673 | U58: =IFERROR($T58*$H58/1000,"") -> 838886.55
A59: Cote d'Ivoire | B59: Savanes | C59: 670068.57 | D59: =SUM(345340+966516+557866) -> 1869722 | E59: =SUM(295231+885524+494022) -> 1674777 | H59: 2282668 | I59: 0 | J59: 184 | K59: 124.1 | L59: =IFERROR($H59*J59/100000,"") -> 4200.1091 | M59: =IFERROR($H59*K59/100000,"") -> 2832.791 | N59: 11.7286 | O59: 2.1995 | P59: 9.79 | Q59: 97.875 | R59: 0.125 | S59: 186652.11 | T59: 252.784 | U59: =IFERROR($T59*$H59/1000,"") -> 577021.95
A60: Cote d'Ivoire | B60: Vallée du Bandama | C60: 533213.56 | D60: =SUM(1034825+570713) -> 1605538 | E60: =SUM(917726+490145) -> 1407871 | H60: 2077052 | I60: 0 | J60: 184 | K60: 124.1 | L60: =IFERROR($H60*J60/100000,"") -> 3821.7757 | M60: =IFERROR($H60*K60/100000,"") -> 2577.6215 | N60: 11.7286 | O60: 2.1995 | P60: 9.79 | Q60: 97.875 | R60: 0.125 | S60: 186652.11 | T60: 247.103 | U60: =IFERROR($T60*$H60/1000,"") -> 513245.78
A61: Cote d'Ivoire | B61: Woroba | C61: 443317.51 | D61: =SUM(244278+456240+398272) -> 1098790 | E61: =SUM(215332+402169+361328) -> 978829 | H61: 1252420 | I61: 0 | J61: 184 | K61: 124.1 | L61: =IFERROR($H61*J61/100000,"") -> 2304.4528 | M61: =IFERROR($H61*K61/100000,"") -> 1554.2532 | N61: 11.7286 | O61: 2.1995 | P61: 9.79 | Q61: 97.875 | R61: 0.125 | S61: 186652.11 | T61: 324.221 | U61: =IFERROR($T61*$H61/1000,"") -> 406060.86
A62: Cote d'Ivoire | B62: Yamoussoukro (Autonomous District) | C62: 107278.72 | D62: 396047 | E62: 349486 | H62: 446158 | I62: 0 | J62: 184 | K62: 124.1 | L62: =IFERROR($H62*J62/100000,"") -> 820.93072 | M62: =IFERROR($H62*K62/100000,"") -> 553.68208 | N62: 11.7286 | O62: 2.1995 | P62: 9.79 | Q62: 97.875 | R62: 0.125 | S62: 186652.11 | T62: 194.649 | U62: =IFERROR($T62*$H62/1000,"") -> 86844.209
A63: Cote d'Ivoire | B63: Zanzan | C63: 337390.69 | D63: =SUM(392678+855420) -> 1248098 | E63: =SUM(374423+740862) -> 1115285 | H63: 1421612 | I63: 0 | J63: 184 | K63: 124.1 | L63: =IFERROR($H63*J63/100000,"") -> 2615.7661 | M63: =IFERROR($H63*K63/100000,"") -> 1764.2205 | N63: 11.7286 | O63: 2.1995 | P63: 9.79 | Q63: 97.875 | R63: 0.125 | S63: 186652.11 | T63: 236.587 | U63: =IFERROR($T63*$H63/1000,"") -> 336334.92
A64: Democratic Republic of the Congo | B64: Bas-Uele | C64: 488330.75 | D64: 460347 | E64: 444843 | F64: 947939 | G64: 922906 | H64: 1690938 | I64: 52.240455 | J64: 888.4 | K64: 435.1 | L64: =IFERROR($H64*J64/100000,"") -> 15022.293 | M64: =IFERROR($H64*K64/100000,"") -> 7357.2712 | N64: 1.8989 | O64: 0.6104 | P64: 28.5 | Q64: 36.035 | R64: 0.23 | S64: 73887.329 | T64: 391.391 | U64: =IFERROR($T64*$H64/1000,"") -> 661817.91
A65: Democratic Republic of the Congo | B65: Equateur | C65: 679460.24 | D65: 267597 | E65: 242429 | F65: 1224128 | G65: 1206848 | H65: 3124410 | I65: 6.0008333 | J65: 888.4 | K65: 435.1 | L65: =IFERROR($H65*J65/100000,"") -> 27757.258 | M65: =IFERROR($H65*K65/100000,"") -> 13594.308 | N65: 1.8989 | O65: 0.6104 | P65: 28.5 | Q65: 36.035 | R65: 0.23 | S65: 73887.329 | T65: 343.489 | U65: =IFERROR($T65*$H65/1000,"") -> 1073200.5
A66: Democratic Republic of the Congo | B66: Haut-Katanga | C66: 2253913 | D66: 363953 | E66: 346487 | F66: 2293988 | G66: 2144756 | H66: 6741023 | I66: 0.0275 | J66: 888.4 | K66: 435.1 | L66: =IFERROR($H66*J66/100000,"") -> 59887.248 | M66: =IFERROR($H66*K66/100000,"") -> 29330.191 | N66: 1.8989 | O66: 0.6104 | P66: 28.5 | Q66: 36.035 | R66: 0.23 | S66: 73887.329 | T66: 255.661 | U66: =IFERROR($T66*$H66/1000,"") -> 1723416.7
A67: Democratic Republic of the Congo | B67: Haut-Lomami | C67: 2056119.2 | D67: 302423 | E67: 302223 | F67: 333147 | G67: 545286 | H67: 4727641 | I67: 0.681875 | J67: 888.4 | K67: 435.1 | L67: =IFERROR($H67*J67/100000,"") -> 42000.363 | M67: =IFERROR($H67*K67/100000,"") -> 20569.966 | N67: 1.8989 | O67: 0.6104 | P67: 28.5 | Q67: 36.035 | R67: 0.23 | S67: 73887.329 | T67: 314.683 | U67: =IFERROR($T67*$H67/1000,"") -> 1487708.3
A68: Democratic Republic of the Congo | B68: Haut-Uele | C68: 676441.49 | D68: 508606 | E68: 463516 | F68: 1119151 | G68: 1085101 | H68: 2347741 | I68: 49.893462 | J68: 888.4 | K68: 435.1 | L68: =IFERROR($H68*J68/100000,"") -> 20857.331 | M68: =IFERROR($H68*K68/100000,"") -> 10215.021 | N68: 1.8989 | O68: 0.6104 | P68: 28.5 | Q68: 36.035 | R68: 0.23 | S68: 73887.329 | T68: 387.99 | U68: =IFERROR($T68*$H68/1000,"") -> 910900.03
A69: Democratic Republic of the Congo | B69: Ituri | C69: 1660479.1 | D69: 2825374 | E69: 2810238 | F69: 1775814 | G69: 1761313 | H69: 6718463 | I69: 24.219444 | J69: 888.4 | K69: 435.1 | L69: =IFERROR($H69*J69/100000,"") -> 59686.825 | M69: =IFERROR($H69*K69/100000,"") -> 29232.033 | N69: 1.8989 | O69: 0.6104 | P69: 28.5 | Q69: 36.035 | R69: 0.23 | S69: 73887.329 | T69: 329.817 | U69: =IFERROR($T69*$H69/1000,"") -> 2215863.3
A70: Democratic Republic of the Congo | B70: Kasai | C70: 1810061.4 | D70: 3842297 | E70: 3669860 | H70: 4599825 | I70: 2.7941667 | J70: 888.4 | K70: 435.1 | L70: =IFERROR($H70*J70/100000,"") -> 40864.845 | M70: =IFERROR($H70*K70/100000,"") -> 20013.839 | N70: 1.8989 | O70: 0.6104 | P70: 28.5 | Q70: 36.035 | R70: 0.23 | S70: 73887.329 | T70: 350.676 | U70: =IFERROR($T70*$H70/1000,"") -> 1613048.2
A71: Democratic Republic of the Congo | B71: Kasai-Central | C71: 2040736.1 | D71: 4937413 | E71: 4817763 | H71: 5870532 | I71: 0.83730769 | J71: 888.4 | K71: 435.1 | L71: =IFERROR($H71*J71/100000,"") -> 52153.806 | M71: =IFERROR($H71*K71/100000,"") -> 25542.685 | N71: 1.8989 | O71: 0.6104 | P71: 28.5 | Q71: 36.035 | R71: 0.23 | S71: 73887.329 | T71: 343.816 | U71: =IFERROR($T71*$H71/1000,"") -> 2018382.8
A72: Democratic Republic of the Congo | B72: Kasai-Oriental | C72: 1148030.1 | D72: 1884696 | E72: 1853187 | H72: 5696823 | I72: 0 | J72: 888.4 | K72: 435.1 | L72: =IFERROR($H72*J72/100000,"") -> 50610.576 | M72: =IFERROR($H72*K72/100000,"") -> 24786.877 | N72: 1.8989 | O72: 0.6104 | P72: 28.5 | Q72: 36.035 | R72: 0.23 | S72: 73887.329 | T72: 228.536 | U72: =IFERROR($T72*$H72/1000,"") -> 1301929.1
A73: Democratic Republic of the Congo | B73: Kinshasa | C73: 2430280.3 | D73: 664842 | E73: 634921 | H73: 10939009 | I73: 21.074429 | J73: 888.4 | K73: 435.1 | L73: =IFERROR($H73*J73/100000,"") -> 97182.156 | M73: =IFERROR($H73*K73/100000,"") -> 47595.628 | N73: 1.8989 | O73: 0.6104 | P73: 28.5 | Q73: 36.035 | R73: 0.23 | S73: 73887.329 | T73: 371.639 | U73: =IFERROR($T73*$H73/1000,"") -> 4065362.4
A74: Democratic Republic of the Congo | B74: Kongo-Central | C74: 813666.89 | D74: 1601344 | E74: 1616914 | H74: 4683560 | I74: 23.751129 | J74: 888.4 | K74: 435.1 | L74: =IFERROR($H74*J74/100000,"") -> 41608.747 | M74: =IFERROR($H74*K74/100000,"") -> 20378.17 | N74: 1.8989 | O74: 0.6104 | P74: 28.5 | Q74: 36.035 | R74: 0.23 | S74: 73887.329 | T74: 332.66 | U74: =IFERROR($T74*$H74/1000,"") -> 1558033.1
A75: Democratic Republic of the Congo | B75: Kwango | C75: 697245.93 | D75: 1242839 | E75: 1218330 | F75: 525632 | G75: 524743 | H75: 3130805 | I75: 5.9482143 | J75: 888.4 | K75: 435.1 | L75: =IFERROR($H75*J75/100000,"") -> 27814.072 | M75: =IFERROR($H75*K75/100000,"") -> 13622.133 | N75: 1.8989 | O75: 0.6104 | P75: 28.5 | Q75: 36.035 | R75: 0.23 | S75: 73887.329 | T75: 362.094 | U75: =IFERROR($T75*$H75/1000,"") -> 1133645.7
A76: Democratic Republic of the Congo | B76: Kwilu | C76: 1383071.2 | D76: 2303180 | E76: 2204097 | H76: 6374629 | I76: 4.389375 | J76: 888.4 | K76: 435.1 | L76: =IFERROR($H76*J76/100000,"") -> 56632.204 | M76: =IFERROR($H76*K76/100000,"") -> 27736.011 | N76: 1.8989 | O76: 0.6104 | P76: 28.5 | Q76: 36.035 | R76: 0.23 | S76: 73887.329 | T76: 377.058 | U76: =IFERROR($T76*$H76/1000,"") -> 2403604.9
A77: Democratic Republic of the Congo | B77: Lomami | C77: 1200111.2 | D77: 3373852 | E77: 3301602 | F77: 273326 | G77: 268201 | H77: 4826171 | I77: 2.2621875 | J77: 888.4 | K77: 435.1 | L77: =IFERROR($H77*J77/100000,"") -> 42875.703 | M77: =IFERROR($H77*K77/100000,"") -> 20998.67 | N77: 1.8989 | O77: 0.6104 | P77: 28.5 | Q77: 36.035 | R77: 0.23 | S77: 73887.329 | T77: 352.206 | U77: =IFERROR($T77*$H77/1000,"") -> 1699806.4
A78: Democratic Republic of the Congo | B78: Lualaba | C78: 1229473.8 | D78: 726022 | E78: 710291 | F78: 119062 | G78: 116561 | H78: 2805949 | I78: 0.05923077 | J78: 888.4 | K78: 435.1 | L78: =IFERROR($H78*J78/100000,"") -> 24928.051 | M78: =IFERROR($H78*K78/100000,"") -> 12208.684 | N78: 1.8989 | O78: 0.6104 | P78: 28.5 | Q78: 36.035 | R78: 0.23 | S78: 73887.329 | T78: 324.24 | U78: =IFERROR($T78*$H78/1000,"") -> 909800.9
A79: Democratic Republic of the Congo | B79: Mai-Ndombe | C79: 466271.05 | F79: 238202 | G79: 221784 | H79: 2432500 | I79: 12.173571 | J79: 888.4 | K79: 435.1 | L79: =IFERROR($H79*J79/100000,"") -> 21610.33 | M79: =IFERROR($H79*K79/100000,"") -> 10583.808 | N79: 1.8989 | O79: 0.6104 | P79: 28.5 | Q79: 36.035 | R79: 0.23 | S79: 73887.329 | T79: 327.306 | U79: =IFERROR($T79*$H79/1000,"") -> 796171.84
A80: Democratic Republic of the Congo | B80: Maniema | C80: 692796.36 | D80: 2433160 | E80: 2389420 | H80: 3418095 | I80: 29.895833 | J80: 888.4 | K80: 435.1 | L80: =IFERROR($H80*J80/100000,"") -> 30366.356 | M80: =IFERROR($H80*K80/100000,"") -> 14872.131 | N80: 1.8989 | O80: 0.6104 | P80: 28.5 | Q80: 36.035 | R80: 0.23 | S80: 73887.329 | T80: 275.216 | U80: =IFERROR($T80*$H80/1000,"") -> 940714.43
A81: Democratic Republic of the Congo | B81: Mongala | C81: 707705.64 | D81: 1245068 | E81: 1183226 | F81: 1079415 | G81: 1086762 | H81: 3179814 | I81: 22.32 | J81: 888.4 | K81: 435.1 | L81: =IFERROR($H81*J81/100000,"") -> 28249.468 | M81: =IFERROR($H81*K81/100000,"") -> 13835.371 | N81: 1.8989 | O81: 0.6104 | P81: 28.5 | Q81: 36.035 | R81: 0.23 | S81: 73887.329 | T81: 374.501 | U81: =IFERROR($T81*$H81/1000,"") -> 1190843.5
A82: Democratic Republic of the Congo | B82: Nord-Kivu | C82: 1112332.3 | D82: 1434931 | E82: 1262856 | F82: 1174491 | G82: 1043871 | H82: 10397972 | I82: 6.7135294 | J82: 888.4 | K82: 435.1 | L82: =IFERROR($H82*J82/100000,"") -> 92375.583 | M82: =IFERROR($H82*K82/100000,"") -> 45241.576 | N82: 1.8989 | O82: 0.6104 | P82: 28.5 | Q82: 36.035 | R82: 0.23 | S82: 73887.329 | T82: 145.569 | U82: =IFERROR($T82*$H82/1000,"") -> 1513622.4
A83: Democratic Republic of the Congo | B83: Nord-Ubangi | C83: 518395.51 | D83: 214361 | E83: 209763 | F83: 955232 | G83: 935221 | H83: 1953747 | I83: 29.187273 | J83: 888.4 | K83: 435.1 | L83: =IFERROR($H83*J83/100000,"") -> 17357.088 | M83: =IFERROR($H83*K83/100000,"") -> 8500.7532 | N83: 1.8989 | O83: 0.6104 | P83: 28.5 | Q83: 36.035 | R83: 0.23 | S83: 73887.329 | T83: 401.85 | U83: =IFERROR($T83*$H83/1000,"") -> 785113.23
A84: Democratic Republic of the Congo | B84: Sankuru | C84: 1008768.7 | D84: 1426804 | E84: 1371749 | H84: 2822775 | I84: 8.386875 | J84: 888.4 | K84: 435.1 | L84: =IFERROR($H84*J84/100000,"") -> 25077.533 | M84: =IFERROR($H84*K84/100000,"") -> 12281.894 | N84: 1.8989 | O84: 0.6104 | P84: 28.5 | Q84: 36.035 | R84: 0.23 | S84: 73887.329 | T84: 334.357 | U84: =IFERROR($T84*$H84/1000,"") -> 943814.58
A85: Democratic Republic of the Congo | B85: Sud-Ubangi | C85: 955691.53 | D85: 215287 | E85: 205872 | F85: 1611886 | G85: 1558572 | H85: 3738949 | I85: 37.900937 | J85: 888.4 | K85: 435.1 | L85: =IFERROR($H85*J85/100000,"") -> 33216.823 | M85: =IFERROR($H85*K85/100000,"") -> 16268.167 | N85: 1.8989 | O85: 0.6104 | P85: 28.5 | Q85: 36.035 | R85: 0.23 | S85: 73887.329 | T85: 378.448 | U85: =IFERROR($T85*$H85/1000,"") -> 1414997.8
A86: Democratic Republic of the Congo | B86: Tanganyika | C86: 1454978.4 | D86: 326949 | E86: 321274 | F86: 707476 | G86: 697824 | H86: 3854132 | I86: 4.0718182 | J86: 888.4 | K86: 435.1 | L86: =IFERROR($H86*J86/100000,"") -> 34240.109 | M86: =IFERROR($H86*K86/100000,"") -> 16769.328 | N86: 1.8989 | O86: 0.6104 | P86: 28.5 | Q86: 36.035 | R86: 0.23 | S86: 73887.329 | T86: 319.432 | U86: =IFERROR($T86*$H86/1000,"") -> 1231133.1
A87: Democratic Republic of the Congo | B87: Tshopo | C87: 1130393.8 | D87: 388521 | E87: 361165 | F87: 2562113 | G87: 2344430 | H87: 4155240 | I87: 33.712391 | J87: 888.4 | K87: 435.1 | L87: =IFERROR($H87*J87/100000,"") -> 36915.152 | M87: =IFERROR($H87*K87/100000,"") -> 18079.449 | N87: 1.8989 | O87: 0.6104 | P87: 28.5 | Q87: 36.035 | R87: 0.23 | S87: 73887.329 | T87: 390.787 | U87: =IFERROR($T87*$H87/1000,"") -> 1623813.8
A88: Democratic Republic of the Congo | B88: Tshuapa | C88: 620015.5 | D88: 597460 | E88: 604223 | F88: 1360313 | G88: 1341077 | H88: 2444717 | I88: 11.167917 | J88: 888.4 | K88: 435.1 | L88: =IFERROR($H88*J88/100000,"") -> 21718.866 | M88: =IFERROR($H88*K88/100000,"") -> 10636.964 | N88: 1.8989 | O88: 0.6104 | P88: 28.5 | Q88: 36.035 | R88: 0.23 | S88: 73887.329 | T88: 445.964 | U88: =IFERROR($T88*$H88/1000,"") -> 1090255.8
A89: Ethiopia | B89: Amhara | C89: 1759415.1 | D89: 1497898 | E89: 1001783 | F89: 492830 | G89: 451609 | H89: 23877520 | I89: 0 | J89: 31.5 | K89: 2.3 | L89: =IFERROR($H89*J89/100000,"") -> 7521.4188 | M89: =IFERROR($H89*K89/100000,"") -> 549.18296 | N89: 3.334 | O89: 0.7815 | P89: 14.1 | Q89: 96.125 | R89: 0.126 | S89: 273512.2 | T89: 72.258 | U89: =IFERROR($T89*$H89/1000,"") -> 1725341.8
A90: Ethiopia | B90: Benishangul Gumz | C90: 175847.21 | D90: 934316 | E90: 779819 | F90: 168306 | G90: 129937 | H90: 1275883 | I90: 0 | J90: 31.5 | K90: 2.3 | L90: =IFERROR($H90*J90/100000,"") -> 401.90314 | M90: =IFERROR($H90*K90/100000,"") -> 29.345309 | N90: 3.334 | O90: 0.7815 | P90: 14.1 | Q90: 96.125 | R90: 0.126 | S90: 273512.2 | T90: 104.991 | U90: =IFERROR($T90*$H90/1000,"") -> 133956.23
A91: Ethiopia | B91: Gambela | C91: 52613.185 | D91: 64331 | E91: 57187 | F91: 75595 | G91: 70983 | H91: 603099 | I91: 0 | J91: 31.5 | K91: 2.3 | L91: =IFERROR($H91*J91/100000,"") -> 189.97618 | M91: =IFERROR($H91*K91/100000,"") -> 13.871277 | N91: 3.334 | O91: 0.7815 | P91: 14.1 | Q91: 96.125 | R91: 0.126 | S91: 273512.2 | T91: 94.309 | U91: =IFERROR($T91*$H91/1000,"") -> 56877.664
A92: Ethiopia | B92: Oromia | C92: 3332947.2 | D92: 16829525 | E92: 15714405 | F92: 1128960 | G92: 932817 | H92: 44158759 | I92: 0 | J92: 31.5 | K92: 2.3 | L92: =IFERROR($H92*J92/100000,"") -> 13910.009 | M92: =IFERROR($H92*K92/100000,"") -> 1015.6515 | N92: 3.334 | O92: 0.7815 | P92: 14.1 | Q92: 96.125 | R92: 0.126 | S92: 273512.2 | T92: 73.466 | U92: =IFERROR($T92*$H92/1000,"") -> 3244167.4
A93: Ethiopia | B93: Sidama | C93: 275026.57 | F93: 136440 | G93: 127917 | H93: 4851008 | I93: 0 | J93: 31.5 | K93: 2.3 | L93: =IFERROR($H93*J93/100000,"") -> 1528.0675 | M93: =IFERROR($H93*K93/100000,"") -> 111.57318 | N93: 3.334 | O93: 0.7815 | P93: 14.1 | Q93: 96.125 | R93: 0.126 | S93: 273512.2 | T93: 58.212 | U93: =IFERROR($T93*$H93/1000,"") -> 282386.88
A94: Ethiopia | B94: Snnp | C94: 1636426.6 | D94: =SUM(344838+2162995) -> 2507833 | E94: =SUM(345688+2022106) -> 2367794 | F94: 691331 | G94: 686206 | H94: 14279320 | I94: 0 | J94: 31.5 | K94: 2.3 | L94: =IFERROR($H94*J94/100000,"") -> 4497.9858 | M94: =IFERROR($H94*K94/100000,"") -> 328.42436 | N94: 3.334 | O94: 0.7815 | P94: 14.1 | Q94: 96.125 | R94: 0.126 | S94: 273512.2 | T94: 86.051 | U94: =IFERROR($T94*$H94/1000,"") -> 1228749.8
A95: Ghana | B95: Ahafo | C95: 117939.49 | D95: 227382 | E95: 192902 | H95: 571893 | I95: 0 | J95: 1498.4 | K95: 106.7 | L95: =IFERROR($H95*J95/100000,"") -> 8569.2447 | M95: =IFERROR($H95*K95/100000,"") -> 610.20983 | N95: 9.0957 | O95: 1.8033 | P95: 9.785 | Q95: 97.875 | R95: 0.104 | S95: 139488.62 | T95: 192.356 | U95: =IFERROR($T95*$H95/1000,"") -> 110007.05
A96: Ghana | B96: Ashanti | C96: 1066191.3 | D96: 499069 | E96: 414065 | H96: 5670664 | I96: 0 | J96: 1498.4 | K96: 106.7 | L96: =IFERROR($H96*J96/100000,"") -> 84969.229 | M96: =IFERROR($H96*K96/100000,"") -> 6050.5985 | N96: 9.0957 | O96: 1.8033 | P96: 9.785 | Q96: 97.875 | R96: 0.104 | S96: 139488.62 | T96: 155.716 | U96: =IFERROR($T96*$H96/1000,"") -> 883013.12
A97: Ghana | B97: Bono | C97: 227991.26 | D97: 104635 | E97: 89536 | F97: 117804 | G97: 78785 | H97: 1259944 | I97: 0 | J97: 1498.4 | K97: 106.7 | L97: =IFERROR($H97*J97/100000,"") -> 18879.001 | M97: =IFERROR($H97*K97/100000,"") -> 1344.3602 | N97: 9.0957 | O97: 1.8033 | P97: 9.785 | Q97: 97.875 | R97: 0.104 | S97: 139488.62 | T97: 196.529 | U97: =IFERROR($T97*$H97/1000,"") -> 247615.53
A98: Ghana | B98: Bono East | C98: 247456.78 | D98: 788209 | E98: 642291 | F98: 116300 | G98: 79875 | H98: 1224331 | I98: 0 | J98: 1498.4 | K98: 106.7 | L98: =IFERROR($H98*J98/100000,"") -> 18345.376 | M98: =IFERROR($H98*K98/100000,"") -> 1306.3612 | N98: 9.0957 | O98: 1.8033 | P98: 9.785 | Q98: 97.875 | R98: 0.104 | S98: 139488.62 | T98: 207.266 | U98: =IFERROR($T98*$H98/1000,"") -> 253762.19
A99: Ghana | B99: Central | C99: 542151.77 | D99: 146603 | E99: 114229 | H99: 2981714 | I99: 0 | J99: 1498.4 | K99: 106.7 | L99: =IFERROR($H99*J99/100000,"") -> 44678.003 | M99: =IFERROR($H99*K99/100000,"") -> 3181.4888 | N99: 9.0957 | O99: 1.8033 | P99: 9.785 | Q99: 97.875 | R99: 0.104 | S99: 139488.62 | T99: 184.619 | U99: =IFERROR($T99*$H99/1000,"") -> 550481.06
A100: Ghana | B100: Eastern | C100: 670923 | D100: 100361 | E100: 83521 | H100: 3049825 | I100: 0 | J100: 1498.4 | K100: 106.7 | L100: =IFERROR($H100*J100/100000,"") -> 45698.578 | M100: =IFERROR($H100*K100/100000,"") -> 3254.1633 | N100: 9.0957 | O100: 1.8033 | P100: 9.785 | Q100: 97.875 | R100: 0.104 | S100: 139488.62 | T100: 195.548 | U100: =IFERROR($T100*$H100/1000,"") -> 596387.18
A101: Ghana | B101: Greater Accra | C101: 792210.24 | D101: 50457 | E101: 32350 | H101: 5687240 | I101: 0 | J101: 1498.4 | K101: 106.7 | L101: =IFERROR($H101*J101/100000,"") -> 85217.604 | M101: =IFERROR($H101*K101/100000,"") -> 6068.2851 | N101: 9.0957 | O101: 1.8033 | P101: 9.785 | Q101: 97.875 | R101: 0.104 | S101: 139488.62 | T101: 139.125 | U101: =IFERROR($T101*$H101/1000,"") -> 791237.27
...

Sheet Sheet2
A1: Country | B1: District | C1: Senior Program Mgr salary (mean) | D1: District Health Officer salary (mean) | E1: Fuel prices (Gasoline prices) USD
A2: Angola | B2: Bengo | C2: 46500 | D2: 12600 | E2: 0.327
A3: Angola | B3: Bie | C3: 46500.5 | D3: 12600 | E3: 0.327
A4: Angola | B4: Cuando Cubango | C4: 46501 | D4: 12600 | E4: 0.327
A5: Angola | B5: Cuanza Norte | C5: 46501.5 | D5: 12600 | E5: 0.327
A6: Angola | B6: Cuanza Sul | C6: 46502 | D6: 12600 | E6: 0.327
A7: Angola | B7: Huambo | C7: 46502.5 | D7: 12600 | E7: 0.327
A8: Angola | B8: Huila | C8: 46503 | D8: 12600 | E8: 0.327
A9: Angola | B9: Lunda Sul | C9: 46503.5 | D9: 12600 | E9: 0.327
A10: Angola | B10: Uige | C10: 46504 | D10: 12600 | E10: 0.327
A11: Benin | B11: Alibori | C11: 84037.815 | D11: 10500 | E11: 1.288
A12: Benin | B12: Atakora | C12: 84037.815 | D12: 10500 | E12: 1.288
A13: Benin | B13: Atlantique | C13: 84037.815 | D13: 10500 | E13: 1.288
... A203: Uganda | B203: Western | C203: 35598.01 | D203: 9900 | E203: 1.656

Sheet Sheet3
A1: Values for Ratios | B1: derived from: https://pmc.ncbi.nlm.nih.gov/articles/PMC7491157/” | E1: Source
A3: km_region | B3: 44.5 | C3: km | D3: mean distance from district centre to regional centre (one-way)
A4: fuel | B4: 0.12 | C4: USD, km | D4: USD per km of fuel in Toyota Cruiser
A5: food | B5: 8.1 | C5: USD, km | D5: Food allowance per meeting day per person
A7: leaflet | B7: 0.05 | C7: USD/unit | D7: price of a printed colour leaflet, A4
A8: district_dsa | B8: 17.07 | C8: USD/day | D8: District worker DSA
A9: district_wage | B9: 982.12 | C9: USD/day | D9: Cost of a district staff members wage
A10: central_regional_dsa | B10: 19.22 | C10: USD/day | D10: Cost of a central staff members per diem | E10: MACEPA mostly
A11: central_regional_wage | B11: 964.19 | C11: USD per month | D11: Mean monthly wage of program staff at central level
A12: driver_wage | B12: 310.5 | C12: USD/day | D12: Cost of a driver staff members wage
A17: drug_vol | B17: 82.32 | C17: cm3, per course | D17: Drug volume
A18: electricity | B18: 0.24 | C18: USD, kWh | D18: Price of electricity per Kwh
A22: chw_n_cen_plan_c | B22: 10 | C22: number | D22: planning meeting at central level - attendants from central level
A23: chw_n_cen_plan_d | B23: 5 | C23: number | D23: planning meeting at central level - attendants from district level
A24: chw_n_cen_plan_Days | B24: 3 | C24: number | D24: planning meeting days at central level
A25: chw_n_cen_plan_r | B25: 4 | C25: number | D25: planning meeting at central level - attendants from regional level
A26: chw_n_plan_c | B26: 10 | C26: number | D26: Micro Planning - attendants from central level
A27: chw_n_plan_d | B27: 6 | C27: number | D27: Micro Planning - attendants from district level
A28: chw_n_plan_r | B28: 2 | C28: number | D28: Micro Planning - attendants from regional level
A30: MDA_Days_plan_d | B30: 4 | C30: Days | D30: Days micro-planning intervention at district level
A31: MDA_Days_plan_r | B31: 4 | C31: Days | D31: Days micro-planning intervention at regional level
A33: cheap_hotel | B33: 28.99 | C33: USD | D33: cost of night accommodation in cheap hotel | E33: MACEPA/ zambia
A35: Combined Planning Cost per Country — one-day district planning meeting
A37: Meeting assumptions
A38: n_district_attendants | B38: 4 | C38: number | D38: District attendants per meeting
A39: meeting_days | B39: 1 | C39: days | D39: Meeting duration (one whole day)
A40: hotel_nights | B40: 1 | C40: nights | D40: Nights of accommodation for district workers
A41: leaflet_copies | B41: 1000 | C41: copies | D41: Printed leaflets per meeting
A42: round_trip_factor | B42: 2 | C42: number | D42: km_region is one-way, so ×2 for round trip
A43: working_days_per_year | B43: 260 | C43: days | D43: To convert annual salary to daily wage
A44: vehicle_consumption | B44: 0.13 | C44: L/km | D44: Fuel consumption of vehicle (to convert USD/L to USD/km)
A45: Country | B45: Fuel price (USD/L) | C45: Fuel ratio (USD/km vs 0.12 base) | D45: Transport (USD) | E45: Food (USD) | F45: Leaflets (USD) | G45: Accommodation (USD) | H45: DSA (USD) | I45: Staff time (USD) | J45: Total planning cost (USD)
A46: {=_xlfn.UNIQUE(Sheet2!A2:A203)} -> Angola | B46: =AVERAGEIF(Sheet2!$A$2:$A$203,$A46,Sheet2!$E$2:$E$203) -> 0.327 | C46: =B46*$B$44/$B$4 -> 0.35425 | D46: =$B$3*$B$42*$B$4*$C46 -> 3.78339 | E46: =$B$5*$C46*$B$38*$B$39 -> 11.4777 | F46: =$B$7*$B$41*$C46 -> 17.7125 | G46: =$B$33*$C46*$B$38*$B$40 -> 41.07883 | H46: =$B$8*$C46*$B$38*$B$39 -> 24.18819 | I46: =AVERAGEIF(Sheet2!$A$2:$A$203,$A46,Sheet2!$D$2:$D$203)/$B$43*$B$38*$B$39 -> 193.84615 | J46: =SUM(D46:I46) -> 292.08676
A47: Benin | B47: =AVERAGEIF(Sheet2!$A$2:$A$203,$A47,Sheet2!$E$2:$E$203) -> 1.288 | C47: =B47*$B$44/$B$4 -> 1.3953333 | D47: =$B$3*$B$42*$B$4*$C47 -> 14.90216 | E47: =$B$5*$C47*$B$38*$B$39 -> 45.2088 | F47: =$B$7*$B$41*$C47 -> 69.766667 | G47: =$B$33*$C47*$B$38*$B$40 -> 161.80285 | H47: =$B$8*$C47*$B$38*$B$39 -> 95.27336 | I47: =AVERAGEIF(Sheet2!$A$2:$A$203,$A47,Sheet2!$D$2:$D$203)/$B$43*$B$38*$B$39 -> 161.53846 | J47: =SUM(D47:I47) -> 548.4923
A48: Burkina Faso | B48: =AVERAGEIF(Sheet2!$A$2:$A$203,$A48,Sheet2!$E$2:$E$203) -> 1.51 | C48: =B48*$B$44/$B$4 -> 1.6358333 | D48: =$B$3*$B$42*$B$4*$C48 -> 17.4707 | E48: =$B$5*$C48*$B$38*$B$39 -> 53.001 | F48: =$B$7*$B$41*$C48 -> 81.791667 | G48: =$B$33*$C48*$B$38*$B$40 -> 189.69123 | H48: =$B$8*$C48*$B$38*$B$39 -> 111.6947 | I48: =AVERAGEIF(Sheet2!$A$2:$A$203,$A48,Sheet2!$D$2:$D$203)/$B$43*$B$38*$B$39 -> 342.92308 | J48: =SUM(D48:I48) -> 796.57238
A49: Burundi | B49: =AVERAGEIF(Sheet2!$A$2:$A$203,$A49,Sheet2!$E$2:$E$203) -> 1.343 | C49: =B49*$B$44/$B$4 -> 1.4549167 | D49: =$B$3*$B$42*$B$4*$C49 -> 15.53851 | E49: =$B$5*$C49*$B$38*$B$39 -> 47.1393 | F49: =$B$7*$B$41*$C49 -> 72.745833 | G49: =$B$33*$C49*$B$38*$B$40 -> 168.71214 | H49: =$B$8*$C49*$B$38*$B$39 -> 99.34171 | I49: =AVERAGEIF(Sheet2!$A$2:$A$203,$A49,Sheet2!$D$2:$D$203)/$B$43*$B$38*$B$39 -> 92.307692 | J49: =SUM(D49:I49) -> 495.78518
A50: Cameroon | B50: =AVERAGEIF(Sheet2!$A$2:$A$203,$A50,Sheet2!$E$2:$E$203) -> 1.491 | C50: =B50*$B$44/$B$4 -> 1.61525 | D50: =$B$3*$B$42*$B$4*$C50 -> 17.25087 | E50: =$B$5*$C50*$B$38*$B$39 -> 52.3341 | F50: =$B$7*$B$41*$C50 -> 80.7625 | G50: =$B$33*$C50*$B$38*$B$40 -> 187.30439 | H50: =$B$8*$C50*$B$38*$B$39 -> 110.28927 | I50: =AVERAGEIF(Sheet2!$A$2:$A$203,$A50,Sheet2!$D$2:$D$203)/$B$43*$B$38*$B$39 -> 84.923077 | J50: =SUM(D50:I50) -> 532.86421
A51: Chad | B51: =AVERAGEIF(Sheet2!$A$2:$A$203,$A51,Sheet2!$E$2:$E$203) -> 0.847 | C51: =B51*$B$44/$B$4 -> 0.91758333 | D51: =$B$3*$B$42*$B$4*$C51 -> 9.79979 | E51: =$B$5*$C51*$B$38*$B$39 -> 29.7297 | F51: =$B$7*$B$41*$C51 -> 45.879167 | G51: =$B$33*$C51*$B$38*$B$40 -> 106.40296 | H51: =$B$8*$C51*$B$38*$B$39 -> 62.65259 | I51: =AVERAGEIF(Sheet2!$A$2:$A$203,$A51,Sheet2!$D$2:$D$203)/$B$43*$B$38*$B$39 -> 133.84615 | J51: =SUM(D51:I51) -> 388.31036
A52: Congo | B52: =AVERAGEIF(Sheet2!$A$2:$A$203,$A52,Sheet2!$E$2:$E$203) -> 0.97 | C52: =B52*$B$44/$B$4 -> 1.0508333 | D52: =$B$3*$B$42*$B$4*$C52 -> 11.2229 | E52: =$B$5*$C52*$B$38*$B$39 -> 34.047 | F52: =$B$7*$B$41*$C52 -> 52.541667 | G52: =$B$33*$C52*$B$38*$B$40 -> 121.85463 | H52: =$B$8*$C52*$B$38*$B$39 -> 71.7509 | I52: =AVERAGEIF(Sheet2!$A$2:$A$203,$A52,Sheet2!$D$2:$D$203)/$B$43*$B$38*$B$39 -> 147.69231 | J52: =SUM(D52:I52) -> 439.10941
A53: Cote d'Ivoire | B53: =AVERAGEIF(Sheet2!$A$2:$A$203,$A53,Sheet2!$E$2:$E$203) -> 1.554 | C53: =B53*$B$44/$B$4 -> 1.6835 | D53: =$B$3*$B$42*$B$4*$C53 -> 17.97978 | E53: =$B$5*$C53*$B$38*$B$39 -> 54.5454 | F53: =$B$7*$B$41*$C53 -> 84.175 | G53: =$B$33*$C53*$B$38*$B$40 -> 195.21866 | H53: =$B$8*$C53*$B$38*$B$39 -> 114.94938 | I53: =AVERAGEIF(Sheet2!$A$2:$A$203,$A53,Sheet2!$D$2:$D$203)/$B$43*$B$38*$B$39 -> 330.76923 | J53: =SUM(D53:I53) -> 797.63745
A54: Democratic Republic of the Congo | B54: =AVERAGEIF(Sheet2!$A$2:$A$203,$A54,Sheet2!$E$2:$E$203) -> 1.183 | C54: =B54*$B$44/$B$4 -> 1.2815833 | D54: =$B$3*$B$42*$B$4*$C54 -> 13.68731 | E54: =$B$5*$C54*$B$38*$B$39 -> 41.5233 | F54: =$B$7*$B$41*$C54 -> 64.079167 | G54: =$B$33*$C54*$B$38*$B$40 -> 148.6124 | H54: =$B$8*$C54*$B$38*$B$39 -> 87.50651 | I54: =AVERAGEIF(Sheet2!$A$2:$A$203,$A54,Sheet2!$D$2:$D$203)/$B$43*$B$38*$B$39 -> 129.23077 | J54: =SUM(D54:I54) -> 484.63946
A55: Ethiopia | B55: =AVERAGEIF(Sheet2!$A$2:$A$203,$A55,Sheet2!$E$2:$E$203) -> 1.051 | C55: =B55*$B$44/$B$4 -> 1.1385833 | D55: =$B$3*$B$42*$B$4*$C55 -> 12.16007 | E55: =$B$5*$C55*$B$38*$B$39 -> 36.8901 | F55: =$B$7*$B$41*$C55 -> 56.929167 | G55: =$B$33*$C55*$B$38*$B$40 -> 132.03012 | H55: =$B$8*$C55*$B$38*$B$39 -> 77.74247 | I55: =AVERAGEIF(Sheet2!$A$2:$A$203,$A55,Sheet2!$D$2:$D$203)/$B$43*$B$38*$B$39 -> 56.769231 | J55: =SUM(D55:I55) -> 372.52116
A56: Ghana | B56: =AVERAGEIF(Sheet2!$A$2:$A$203,$A56,Sheet2!$E$2:$E$203) -> 1.34 | C56: =B56*$B$44/$B$4 -> 1.4516667 | D56: =$B$3*$B$42*$B$4*$C56 -> 15.5038 | E56: =$B$5*$C56*$B$38*$B$39 -> 47.034 | F56: =$B$7*$B$41*$C56 -> 72.583333 | G56: =$B$33*$C56*$B$38*$B$40 -> 168.33527 | H56: =$B$8*$C56*$B$38*$B$39 -> 99.1198 | I56: =AVERAGEIF(Sheet2!$A$2:$A$203,$A56,Sheet2!$D$2:$D$203)/$B$43*$B$38*$B$39 -> 172.37169 | J56: =SUM(D56:I56) -> 574.94789
A57: Guinea | B57: =AVERAGEIF(Sheet2!$A$2:$A$203,$A57,Sheet2!$E$2:$E$203) -> 1.367 | C57: =B57*$B$44/$B$4 -> 1.4809167 | D57: =$B$3*$B$42*$B$4*$C57 -> 15.81619 | E57: =$B$5*$C57*$B$38*$B$39 -> 47.9817 | F57: =$B$7*$B$41*$C57 -> 74.045833 | G57: =$B$33*$C57*$B$38*$B$40 -> 171.7271 | H57: =$B$8*$C57*$B$38*$B$39 -> 101.11699 | I57: =AVERAGEIF(Sheet2!$A$2:$A$203,$A57,Sheet2!$D$2:$D$203)/$B$43*$B$38*$B$39 -> 81.230769 | J57: =SUM(D57:I57) -> 491.91858
A58: Guinea-Bissau | B58: =AVERAGEIF(Sheet2!$A$2:$A$203,$A58,Sheet2!$E$2:$E$203) -> 1.56 | C58: =B58*$B$44/$B$4 -> 1.69 | D58: =$B$3*$B$42*$B$4*$C58 -> 18.0492 | E58: =$B$5*$C58*$B$38*$B$39 -> 54.756 | F58: =$B$7*$B$41*$C58 -> 84.5 | G58: =$B$33*$C58*$B$38*$B$40 -> 195.9724 | H58: =$B$8*$C58*$B$38*$B$39 -> 115.3932 | I58: =AVERAGEIF(Sheet2!$A$2:$A$203,$A58,Sheet2!$D$2:$D$203)/$B$43*$B$38*$B$39 -> 106.15385 | J58: =SUM(D58:I58) -> 574.82465
... A68: Uganda | B68: =AVERAGEIF(Sheet2!$A$2:$A$203,$A68,Sheet2!$E$2:$E$203) -> 1.656 | C68: =B68*$B$44/$B$4 -> 1.794 | D68: =$B$3*$B$42*$B$4*$C68 -> 19.15992 | E68: =$B$5*$C68*$B$38*$B$39 -> 58.1256 | F68: =$B$7*$B$41*$C68 -> 89.7 | G68: =$B$33*$C68*$B$38*$B$40 -> 208.03224 | H68: =$B$8*$C68*$B$38*$B$39 -> 122.49432 | I68: =AVERAGEIF(Sheet2!$A$2:$A$203,$A68,Sheet2!$D$2:$D$203)/$B$43*$B$38*$B$39 -> 152.30769 | J68: =SUM(D68:I68) -> 649.81977
A72: Method
A73: Convert Fuel | B73: USD per km to USD per litre | C73: Toyota Land Cruiser uses roughly 13L/100 km (0.13L/km), country fuel cost per km = price/litre x 0.13 then divide that by 0.12
A74: Fuel Ratio | B74: Country fuel prices/0.12
A75: Transport | B75: 44.5 km × 2 × 0.12 × ratio
A76: Staff time | B76: country-mean District Health Officer salary ÷ 260 × 4 attendants (no ratio since already country specific )
